propylean/__init__.py
propylean/constants.py
propylean/properties.py
propylean/series.py
propylean/settings.py
propylean/streams.py
propylean/validators.py
propylean/equipments/__init__.py
propylean/equipments/abstract_equipment_classes.py
propylean/equipments/exchangers.py
propylean/equipments/generic_equipment_classes.py
propylean/equipments/rotary.py
propylean/equipments/separators.py
propylean/equipments/static.py
propylean/equipments/storages.py
propylean/instruments/__init__.py
propylean/instruments/control.py
propylean/instruments/measurement.py
propylean/instruments/safety.py
propylean-0.3.0.dist-info/LICENSE
propylean-0.3.0.dist-info/METADATA
propylean-0.3.0.dist-info/WHEEL
propylean-0.3.0.dist-info/top_level.txt
propylean-0.3.0.dist-info/RECORD
