Metadata-Version: 2.1
Name: propylean
Version: 0.3.0
Summary: The pandas and pyspark series wrapper for chemical process industries.
Home-page: https://github.com/abhishekvraman/Propylean
Author: Abhishek V Raman
Author-email: 
Project-URL: Bug Tracker, https://github.com/abhishekvraman/Propylean/issues
Classifier: Programming Language :: Python :: 3
Classifier: License :: OSI Approved :: MIT License
Classifier: Operating System :: OS Independent
Classifier: Development Status :: 3 - Alpha
Classifier: Intended Audience :: Manufacturing
Classifier: Topic :: Scientific/Engineering :: Chemistry
Classifier: License :: OSI Approved :: MIT License
Requires-Python: >=3.9
License-File: LICENSE
Requires-Dist: pandas
Requires-Dist: fluids
Requires-Dist: thermo
